klira/__init__.py
klira/sdk/__init__.py
klira/sdk/_di_container.py
klira/sdk/_lazy_imports.py
klira/sdk/adapters/__init__.py
klira/sdk/adapters/agents_adapter.py
klira/sdk/adapters/anthropic_adapter.py
klira/sdk/adapters/base.py
klira/sdk/adapters/crew_ai.py
klira/sdk/adapters/framework_adapter.py
klira/sdk/adapters/gemini_adapter.py
klira/sdk/adapters/guardrail_adapter.py
klira/sdk/adapters/langchain.py
klira/sdk/adapters/langgraph_adapter.py
klira/sdk/adapters/llama_index.py
klira/sdk/adapters/llm_base_adapter.py
klira/sdk/adapters/ollama_adapter.py
klira/sdk/adapters/openai_agents_adapter.py
klira/sdk/adapters/openai_completion_adapter.py
klira/sdk/adapters/openai_responses_adapter.py
klira/sdk/adapters/standard_adapter.py
klira/sdk/analytics/__init__.py
klira/sdk/analytics/processors.py
klira/sdk/cache/__init__.py
klira/sdk/cache/cache_hierarchy.py
klira/sdk/cache/redis_adapter.py
klira/sdk/client/__init__.py
klira/sdk/client/client.py
klira/sdk/config.py
klira/sdk/decorators/__init__.py
klira/sdk/decorators/base.py
klira/sdk/decorators/guardrails.py
klira/sdk/decorators/mcp_guardrails.py
klira/sdk/decorators/policies.py
klira/sdk/evals/README.md
klira/sdk/evals/__init__.py
klira/sdk/evals/ci.py
klira/sdk/evals/convenience.py
klira/sdk/evals/dataset_loader.py
klira/sdk/evals/guardrails_capture.py
klira/sdk/evals/hub_uploader.py
klira/sdk/evals/metrics/__init__.py
klira/sdk/evals/metrics/audit_trail_completeness.py
klira/sdk/evals/metrics/augmentation_effectiveness.py
klira/sdk/evals/metrics/cache_efficiency.py
klira/sdk/evals/metrics/conversation_violation.py
klira/sdk/evals/metrics/directional_enforcement.py
klira/sdk/evals/metrics/fuzzy_match_recall.py
klira/sdk/evals/metrics/guardrails_effectiveness.py
klira/sdk/evals/metrics/layer_confidence.py
klira/sdk/evals/metrics/policy_accuracy.py
klira/sdk/evals/metrics/policy_coverage.py
klira/sdk/evals/runner.py
klira/sdk/evals/types.py
klira/sdk/guardrails/_service_locator.py
klira/sdk/guardrails/augmentation.py
klira-0.4.1.dist-info/METADATA
klira-0.4.1.dist-info/WHEEL
klira-0.4.1.dist-info/licenses/LICENSE
klira-0.4.1.dist-info/licenses/NOTICE
klira-0.4.1.dist-info/RECORD
