Metadata-Version: 2.4
Name: klira
Version: 0.4.1
Summary: Klira AI SDK for LLM observability and policy enforcement
License: Proprietary
License-File: LICENSE
License-File: NOTICE
Keywords: llm,observability,policy,governance,tracing,opentelemetry
Author: Klira AI Team
Author-email: hello@getklira.com
Requires-Python: >=3.10,<4
Classifier: Development Status :: 3 - Alpha
Classifier: Intended Audience :: Developers
Classifier: License :: Other/Proprietary License
Classifier: Programming Language :: Python :: 3
Classifier: Programming Language :: Python :: 3.10
Classifier: Programming Language :: Python :: 3.11
Classifier: Programming Language :: Python :: 3.12
Classifier: Programming Language :: Python :: 3.13
Classifier: Topic :: Software Development :: Libraries :: Python Modules
Requires-Dist: colorama (>=0.4.6)
Requires-Dist: deepeval (>=1.0.0)
Requires-Dist: opentelemetry-api (>=1.28.0)
Requires-Dist: opentelemetry-exporter-otlp-proto-grpc (>=1.28.0)
Requires-Dist: opentelemetry-exporter-otlp-proto-http (>=1.28.0)
Requires-Dist: opentelemetry-sdk (>=1.28.0)
Requires-Dist: pydantic (>=1)
Requires-Dist: rapidfuzz (>=3.14.1)
Requires-Dist: requests (>=2.31.0)
Requires-Dist: traceloop-sdk (>=0.38.12)
Project-URL: Documentation, https://docs.getklira.com
Project-URL: Repository, https://github.com/kliraai/kliraai-sdk
